{
  "name": "checkbox",
  "type": "components:ui",
  "dependencies": [
    "@radix-ui/react-checkbox",
    "class-variance-authority"
  ],
  "registryDependencies": [
    "minus",
    "utils"
  ],
  "files": [
    {
      "path": "components/ui/checkbox.tsx",
      "content": "import {\n  Checkbox as CheckboxRoot,\n  CheckboxIndicator,\n} from \"@radix-ui/react-checkbox\";\nimport { CheckIcon } from \"@/components/ui/icons/check\";\nimport { MinusIcon } from \"@/components/ui/icons/minus\";\nimport { clx } from \"@/lib/utils\";\nimport { cva, type VariantProps } from \"class-variance-authority\";\nimport { ComponentProps, forwardRef, ForwardRefExoticComponent } from \"react\";\n\nconst checkbox_cva = cva(\n  [\n    \"outline-none flex items-center justify-center\",\n    \"border border-otl-gray-200 hover:border-otl-gray-300 shadow-button bg-bg-white\",\n    \"data-[state=checked]:bg-primary-600 data-[state=checked]:border-none data-[state=checked]:hover:border-primary-700 data-[state=checked]:hover:bg-primary-700\",\n    \"data-[state=indeterminate]:bg-primary-600 data-[state=indeterminate]:border-none data-[state=indeterminate]:hover:border-primary-700 data-[state=indeterminate]:hover:bg-primary-700\",\n    \"focus-visible:ring-[3px] focus-visible:ring-fr-primary\",\n    \"focus:ring-[3px] focus:ring-fr-primary\",\n    \"disabled:opacity-30 disabled:cursor-not-allowed disabled:bg-bg-washed data-[state=checked]:disabled:bg-primary-600\",\n  ],\n  {\n    variants: {\n      size: {\n        small: \"size-4 rounded-xs\",\n        medium: \"size-5 rounded-[5px]\",\n        large: \"size-5 rounded-[5px]\",\n      },\n    },\n    defaultVariants: {\n      size: \"small\",\n    },\n  },\n);\n\nconst checkbox_icon_cva = cva(\n  [\n    \"flex items-center justify-center text-white\",\n    \"[&_.minus-icon]:hidden\",\n    \"[&_.checked-icon]:hidden\",\n    \"[&[data-state=checked]_.checked-icon]:inline-block\",\n    \"[&[data-state=indeterminate]_.minus-icon]:inline-block\",\n  ],\n  {\n    variants: {\n      size: {\n        small: \"size-3 stroke-[1.5px]\",\n        medium: \"size-4 stroke-[2px]\",\n        large: \"size-4 stroke-[2px]\",\n      },\n    },\n    defaultVariants: {\n      size: \"small\",\n    },\n  },\n);\n\ninterface CheckboxProps\n  extends ComponentProps<typeof CheckboxRoot>,\n    VariantProps<typeof checkbox_cva> {}\n\nconst Checkbox: ForwardRefExoticComponent<CheckboxProps> = forwardRef(\n  ({ className, size, ...props }, ref) => {\n    return (\n      <CheckboxRoot\n        ref={ref}\n        className={clx(checkbox_cva({ size }), className)}\n        role=\"checkbox\"\n        {...props}\n      >\n        <CheckboxIndicator className={checkbox_icon_cva({ size })}>\n          <MinusIcon className=\"minus-icon\" />\n          <CheckIcon className=\"checked-icon\" />\n        </CheckboxIndicator>\n      </CheckboxRoot>\n    );\n  },\n);\n\nCheckbox.displayName = \"Checkbox\";\n\nexport { Checkbox };\n",
      "type": "components:ui"
    }
  ],
  "tailwind": {
    "config": {
      "theme": {
        "extend": {
          "colors": {}
        }
      }
    }
  }
}