{
  "name": "check",
  "type": "components:icon",
  "dependencies": [],
  "registryDependencies": [],
  "files": [
    {
      "path": "components/ui/icons/check.tsx",
      "content": "import React from \"react\";\nimport { FunctionComponent, SVGProps } from \"react\";\n\n/**\n * Check Icon\n * @param className\n * @returns CheckIcon\n */\nexport const CheckIcon: FunctionComponent<SVGProps<SVGSVGElement>> = (\n  props,\n) => {\n  return (\n    <svg\n      width=\"20\"\n      height=\"20\"\n      viewBox=\"0 0 20 20\"\n      fill=\"none\"\n      xmlns=\"http://www.w3.org/2000/svg\"\n      {...props}\n    >\n      <g id=\"Icon/check\">\n        <path\n          id=\"Vector\"\n          d=\"M4 11.4608L6.71103 14.5373C7.36204 15.276 8.53625 15.1978 9.08347 14.3792L16 4.0322\"\n          stroke=\"currentColor\"\n          strokeWidth=\"10%\"\n          strokeLinecap=\"round\"\n          strokeLinejoin=\"round\"\n        />\n      </g>\n    </svg>\n  );\n};\n",
      "type": "components:icon"
    }
  ]
}